Workbook

Sheet Resumen
A1: PLANTILLA DE PRESUPUESTO DE PROYECTO DE SOFTWARE
A3: Proyecto | B3: Sistema de gestión
A4: Cliente | B4: Nombre del cliente
A5: Proveedor | B5: Empresa / Consultor
A6: Fecha | B6: 2026-03-27
A7: Duración estimada | B7: 12 semanas
A8: Moneda | B8: COP
A11: Componente | B11: Horas | C11: Tarifa promedio | D11: Costo base | E11: % Contingencia | F11: Total
A12: Análisis y diseño | B12: =SUMIF(Detalle!$B:$B,"Analista",Detalle!$C:$C) -> 200 | C12: =IFERROR(SUMIF(Detalle!$B:$B,"Analista",Detalle!$E:$E)/SUMIF(Detalle!$B:$B,"Analista",Detalle!$C:$C),0) -> 25000 | D12: =SUMIF(Detalle!$B:$B,"Analista",Detalle!$E:$E) -> 5000000 | E12: =Parametros!$B$10 -> 0.1 | F12: =D12*(1+E12) -> 5500000
A13: Diseño UI/UX | B13: =SUMIF(Detalle!$B:$B,"Diseñador UI/UX",Detalle!$C:$C) -> 60 | C13: =IFERROR(SUMIF(Detalle!$B:$B,"Diseñador UI/UX",Detalle!$E:$E)/SUMIF(Detalle!$B:$B,"Diseñador UI/UX",Detalle!$C:$C),0) -> 25000 | D13: =SUMIF(Detalle!$B:$B,"Diseñador UI/UX",Detalle!$E:$E) -> 1500000 | E13: =Parametros!$B$10 -> 0.1 | F13: =D13*(1+E13) -> 1650000
A14: Desarrollo backend | B14: =SUMIF(Detalle!$B:$B,"Desarrollador Backend",Detalle!$C:$C) -> 320 | C14: =IFERROR(SUMIF(Detalle!$B:$B,"Desarrollador Backend",Detalle!$E:$E)/SUMIF(Detalle!$B:$B,"Desarrollador Backend",Detalle!$C:$C),0) -> 40000 | D14: =SUMIF(Detalle!$B:$B,"Desarrollador Backend",Detalle!$E:$E) -> 12800000 | E14: =Parametros!$B$10 -> 0.1 | F14: =D14*(1+E14) -> 14080000
A15: Desarrollo frontend | B15: =SUMIF(Detalle!$B:$B,"Desarrollador Frontend",Detalle!$C:$C) -> 280 | C15: =IFERROR(SUMIF(Detalle!$B:$B,"Desarrollador Frontend",Detalle!$E:$E)/SUMIF(Detalle!$B:$B,"Desarrollador Frontend",Detalle!$C:$C),0) -> 35000 | D15: =SUMIF(Detalle!$B:$B,"Desarrollador Frontend",Detalle!$E:$E) -> 9800000 | E15: =Parametros!$B$10 -> 0.1 | F15: =D15*(1+E15) -> 10780000
A16: Base de datos | B16: =SUMIF(Detalle!$B:$B,"DBA / Arquitectura",Detalle!$C:$C) -> 100 | C16: =IFERROR(SUMIF(Detalle!$B:$B,"DBA / Arquitectura",Detalle!$E:$E)/SUMIF(Detalle!$B:$B,"DBA / Arquitectura",Detalle!$C:$C),0) -> 25000 | D16: =SUMIF(Detalle!$B:$B,"DBA / Arquitectura",Detalle!$E:$E) -> 2500000 | E16: =Parametros!$B$10 -> 0.1 | F16: =D16*(1+E16) -> 2750000
A17: Integraciones | B17: =SUMIF(Detalle!$B:$B,"Integraciones",Detalle!$C:$C) -> 80 | C17: =IFERROR(SUMIF(Detalle!$B:$B,"Integraciones",Detalle!$E:$E)/SUMIF(Detalle!$B:$B,"Integraciones",Detalle!$C:$C),0) -> 25000 | D17: =SUMIF(Detalle!$B:$B,"Integraciones",Detalle!$E:$E) -> 2000000 | E17: =Parametros!$B$10 -> 0.1 | F17: =D17*(1+E17) -> 2200000
A18: QA y pruebas | B18: =SUMIF(Detalle!$B:$B,"QA",Detalle!$C:$C) -> 160 | C18: =IFERROR(SUMIF(Detalle!$B:$B,"QA",Detalle!$E:$E)/SUMIF(Detalle!$B:$B,"QA",Detalle!$C:$C),0) -> 30000 | D18: =SUMIF(Detalle!$B:$B,"QA",Detalle!$E:$E) -> 4800000 | E18: =Parametros!$B$10 -> 0.1 | F18: =D18*(1+E18) -> 5280000
A19: Despliegue | B19: =SUMIF(Detalle!$B:$B,"DevOps",Detalle!$C:$C) -> 50 | C19: =IFERROR(SUMIF(Detalle!$B:$B,"DevOps",Detalle!$E:$E)/SUMIF(Detalle!$B:$B,"DevOps",Detalle!$C:$C),0) -> 30000 | D19: =SUMIF(Detalle!$B:$B,"DevOps",Detalle!$E:$E) -> 1500000 | E19: =Parametros!$B$10 -> 0.1 | F19: =D19*(1+E19) -> 1650000
A20: Documentación y capacitación | B20: =SUMIF(Detalle!$B:$B,"Documentación",Detalle!$C:$C) -> 60 | C20: =IFERROR(SUMIF(Detalle!$B:$B,"Documentación",Detalle!$E:$E)/SUMIF(Detalle!$B:$B,"Documentación",Detalle!$C:$C),0) -> 20000 | D20: =SUMIF(Detalle!$B:$B,"Documentación",Detalle!$E:$E) -> 1200000 | E20: =Parametros!$B$10 -> 0.1 | F20: =D20*(1+E20) -> 1320000
A21: Gestión del proyecto | B21: =SUMIF(Detalle!$B:$B,"Líder de proyecto",Detalle!$C:$C) -> 120 | C21: =IFERROR(SUMIF(Detalle!$B:$B,"Líder de proyecto",Detalle!$E:$E)/SUMIF(Detalle!$B:$B,"Líder de proyecto",Detalle!$C:$C),0) -> 35000 | D21: =SUMIF(Detalle!$B:$B,"Líder de proyecto",Detalle!$E:$E) -> 4200000 | E21: =Parametros!$B$10 -> 0.1 | F21: =D21*(1+E21) -> 4620000
A22: Subtotal servicios | B22: =SUM(B12:B21) -> 1430 | D22: =SUM(D12:D21) -> 45300000 | E22: =AVERAGE(E12:E21) -> 0.1 | F22: =SUM(F12:F21) -> 49830000
A25: Costos adicionales
A26: Infraestructura cloud / hosting | C26: 1500000 | E26: Subtotal adicionales | F26: =SUM(C26:C29) -> 3650000
A27: Licencias / herramientas | C27: 1200000
A28: Dominio / certificados | C28: 150000
A29: Reserva de cambios menores | C29: 800000
E32: Subtotal general | F32: =F22+F26 -> 53480000
E33: Impuesto | F33: =F32*Parametros!$B$11 -> 10161200
E34: TOTAL PROPUESTA | F34: =F32+F33 -> 63641200
A37: Forma de pago sugerida
A38: Anticipo | B38: 0.3 | C38: =$F$34*B38 -> 19092360
A39: Durante desarrollo | B39: 0.4 | C39: =$F$34*B39 -> 25456480
A40: Contra entrega | B40: 0.3 | C40: =$F$34*B40 -> 19092360
A41: Control | B41: =SUM(B38:B40) -> 1 | C41: Debe sumar 100%

Sheet Detalle
A1: Fase | B1: Perfil | C1: Horas | D1: Tarifa/hora | E1: Costo base | F1: Observaciones
A2: Levantamiento y análisis | B2: Analista | C2: 100 | D2: 25000 | E2: =C2*D2 -> 2500000 | F2: Reuniones, historias de usuario y alcance
A3: Diseño funcional y técnico | B3: Analista | C3: 100 | D3: 25000 | E3: =C3*D3 -> 2500000 | F3: Casos de uso, arquitectura y criterios
A4: Diseño UI/UX | B4: Diseñador UI/UX | C4: 60 | D4: 25000 | E4: =C4*D4 -> 1500000 | F4: Flujos, wireframes y prototipos
A5: Backend módulo principal | B5: Desarrollador Backend | C5: 320 | D5: 40000 | E5: =C5*D5 -> 12800000 | F5: API, reglas de negocio y seguridad
A6: Frontend módulo principal | B6: Desarrollador Frontend | C6: 280 | D6: 35000 | E6: =C6*D6 -> 9800000 | F6: Interfaces, validaciones y consumo API
A7: Modelo de datos | B7: DBA / Arquitectura | C7: 100 | D7: 25000 | E7: =C7*D7 -> 2500000 | F7: Diseño lógico y optimización
A8: Integración con terceros | B8: Integraciones | C8: 80 | D8: 25000 | E8: =C8*D8 -> 2000000 | F8: Pasarelas, APIs o servicios externos
A9: Pruebas funcionales | B9: QA | C9: 160 | D9: 30000 | E9: =C9*D9 -> 4800000 | F9: Casos de prueba y defectos
A10: Despliegue y CI/CD | B10: DevOps | C10: 50 | D10: 30000 | E10: =C10*D10 -> 1500000 | F10: Servidor, pipeline y monitoreo
A11: Documentación | B11: Documentación | C11: 40 | D11: 20000 | E11: =C11*D11 -> 800000 | F11: Manual técnico y usuario
A12: Capacitación | B12: Documentación | C12: 20 | D12: 20000 | E12: =C12*D12 -> 400000 | F12: 2 sesiones
A13: Gestión del proyecto | B13: Líder de proyecto | C13: 120 | D13: 35000 | E13: =C13*D13 -> 4200000 | F13: Seguimiento, riesgos y control

Sheet Parametros
A1: Parámetro | B1: Valor | C1: Descripción
A2: Contingencia global | B2: 0.1 | C2: Usada en la hoja Resumen
A3: Impuesto global | B3: 0.19 | C3: Usado en la hoja Resumen
A4: Descuento comercial | B4: 0 | C4: Opcional
A5: Moneda de referencia | B5: COP | C5: Cambiar si aplica
A6: Horas por semana | B6: 40 | C6: Para estimar duración
A10: Contingencia global | B10: =B2 -> 0.1 | C10: Referencia para fórmulas
A11: Impuesto global | B11: =B3 -> 0.19 | C11: Referencia para fórmulas
